Workbook

Sheet Customers_Data
A1: Customer_ID | B1: Customer_Name | C1: Region | D1: Product_Category | E1: Sales | F1: Quantity | G1: Discount | H1: Order_Date | I1: Profit | J1: Total_Purchase | K1: Timestamp
A2: CUST022 | B2: Vikas Nair | C2: East | D2: Electronics | E2: 746.97 | F2: 6 | G2: 0.15 | H2: 45393 | I2: 398.76 | J2: =SUMIF(Table1[Customer_ID],Table1[[#This Row],[Customer_ID]],Table1[Sales]) -> 6978.86 | K2: =NOW() -> 46120.473 | N2: Top_10_Customers | Q2: OUTPUT IN :- Scenario Summary Worksheet
A3: CUST017 | B3: Deepak Singh | C3: East | D3: Furniture | E3: 824.23 | F3: 17 | G3: 0.1 | H3: 45393 | I3: 246.44 | J3: =SUMIF(Table1[Customer_ID],Table1[[#This Row],[Customer_ID]],Table1[Sales]) -> 5612.99 | K3: =NOW() -> 46120.473 | N3: Customer_ID | O3: Sum of Sales | Q3: What IF analysis
A4: CUST016 | B4: Arjun Sharma | C4: Central | D4: Clothing | E4: 1440.5 | F4: 10 | G4: 0.2 | H4: 45399 | I4: 566.53 | J4: =SUMIF(Table1[Customer_ID],Table1[[#This Row],[Customer_ID]],Table1[Sales]) -> 4192.32 | K4: =NOW() -> 46120.473 | N4: CUST015 | O4: 11576.38 | Q4: Sales | R4: =Customers_Data!E2 -> 746.97
A5: CUST014 | B5: Priya Agarwal | C5: East | D5: Electronics | E5: 410.15 | F5: 19 | G5: 0.2 | H5: 45402 | I5: 225.52 | J5: =SUMIF(Table1[Customer_ID],Table1[[#This Row],[Customer_ID]],Table1[Sales]) -> 7755.06 | K5: =NOW() -> 46120.473 | N5: CUST029 | O5: 11216.81 | Q5: Discount | R5: 0.1
A6: CUST013 | B6: Neha Kumar | C6: North | D6: Furniture | E6: 410.73 | F6: 7 | G6: 0.2 | H6: 45402 | I6: 89.42 | J6: =SUMIF(Table1[Customer_ID],Table1[[#This Row],[Customer_ID]],Table1[Sales]) -> 9513.89 | K6: =NOW() -> 46120.473 | N6: CUST025 | O6: 11063.92 | Q6: Formula | R6: =R4*(1-R5) -> 672.273
A7: CUST003 | B7: Neha Iyer | C7: Central | D7: Furniture | E7: 1390.08 | F7: 18 | G7: 0.1 | H7: 45406 | I7: 334.13 | J7: =SUMIF(Table1[Customer_ID],Table1[[#This Row],[Customer_ID]],Table1[Sales]) -> 10564.12 | K7: =NOW() -> 46120.473 | N7: CUST012 | O7: 10890.76
A8: CUST014 | B8: Vikram Sharma | C8: North | D8: Electronics | E8: 1832.45 | F8: 5 | G8: 0.2 | H8: 45410 | I8: 901.76 | J8: =SUMIF(Table1[Customer_ID],Table1[[#This Row],[Customer_ID]],Table1[Sales]) -> 7755.06 | K8: =NOW() -> 46120.473 | N8: CUST003 | O8: 10564.12
A9: CUST009 | B9: Preeti Patel | C9: East | D9: Office Supplies | E9: 381.6 | F9: 15 | G9: 0.15 | H9: 45411 | I9: 83.92 | J9: =SUMIF(Table1[Customer_ID],Table1[[#This Row],[Customer_ID]],Table1[Sales]) -> 8104.79 | K9: =NOW() -> 46120.473 | N9: CUST023 | O9: 10167.54
A10: CUST022 | B10: Nisha Agarwal | C10: East | D10: Office Supplies | E10: 326.63 | F10: 1 | G10: 0 | H10: 45415 | I10: 173.76 | J10: =SUMIF(Table1[Customer_ID],Table1[[#This Row],[Customer_ID]],Table1[Sales]) -> 6978.86 | K10: =NOW() -> 46120.473 | N10: CUST028 | O10: 9958.16
A11: CUST021 | B11: Aarav Gupta | C11: West | D11: Clothing | E11: 551.03 | F11: 17 | G11: 0.15 | H11: 45417 | I11: 217.71 | J11: =SUMIF(Table1[Customer_ID],Table1[[#This Row],[Customer_ID]],Table1[Sales]) -> 8044.2 | K11: =NOW() -> 46120.473 | N11: CUST013 | O11: 9513.89
A12: CUST004 | B12: Anjali Mishra | C12: South | D12: Books | E12: 1763.1 | F12: 2 | G12: 0.1 | H12: 45420 | I12: 533.65 | J12: =SUMIF(Table1[Customer_ID],Table1[[#This Row],[Customer_ID]],Table1[Sales]) -> 4157.53 | K12: =NOW() -> 46120.473 | N12: CUST005 | O12: 8197.96
A13: CUST022 | B13: Preeti Chauhan | C13: Central | D13: Books | E13: 333.67 | F13: 13 | G13: 0.2 | H13: 45420 | I13: 67.63 | J13: =SUMIF(Table1[Customer_ID],Table1[[#This Row],[Customer_ID]],Table1[Sales]) -> 6978.86 | K13: =NOW() -> 46120.473 | N13: CUST009 | O13: 8104.79
A14: CUST004 | B14: Shilpa Iyer | C14: West | D14: Furniture | E14: 1036.06 | F14: 2 | G14: 0 | H14: 45423 | I14: 353.21 | J14: =SUMIF(Table1[Customer_ID],Table1[[#This Row],[Customer_ID]],Table1[Sales]) -> 4157.53 | K14: =NOW() -> 46120.473
A15: CUST015 | B15: Rahul Joshi | C15: North | D15: Books | E15: 1825.81 | F15: 16 | G15: 0 | H15: 45425 | I15: 621.23 | J15: =SUMIF(Table1[Customer_ID],Table1[[#This Row],[Customer_ID]],Table1[Sales]) -> 11576.38 | K15: =NOW() -> 46120.473
A16: CUST013 | B16: Suresh Patel | C16: West | D16: Books | E16: 680.58 | F16: 1 | G16: 0.1 | H16: 45426 | I16: 218.25 | J16: =SUMIF(Table1[Customer_ID],Table1[[#This Row],[Customer_ID]],Table1[Sales]) -> 9513.89 | K16: =NOW() -> 46120.473
A17: CUST028 | B17: Manoj Gupta | C17: Central | D17: Electronics | E17: 836.44 | F17: 14 | G17: 0.1 | H17: 45427 | I17: 315.41 | J17: =SUMIF(Table1[Customer_ID],Table1[[#This Row],[Customer_ID]],Table1[Sales]) -> 9958.16 | K17: =NOW() -> 46120.473
A18: CUST020 | B18: Suresh Rao | C18: North | D18: Clothing | E18: 737.98 | F18: 10 | G18: 0.15 | H18: 45428 | I18: 325.14 | J18: =SUMIF(Table1[Customer_ID],Table1[[#This Row],[Customer_ID]],Table1[Sales]) -> 5289.47 | K18: =NOW() -> 46120.473
A19: CUST003 | B19: Pooja Dubey | C19: West | D19: Office Supplies | E19: 942.38 | F19: 14 | G19: 0.2 | H19: 45429 | I19: 229.81 | J19: =SUMIF(Table1[Customer_ID],Table1[[#This Row],[Customer_ID]],Table1[Sales]) -> 10564.12 | K19: =NOW() -> 46120.473
A20: CUST015 | B20: Anjali Yadav | C20: West | D20: Electronics | E20: 1461.59 | F20: 14 | G20: 0.05 | H20: 45430 | I20: 532.49 | J20: =SUMIF(Table1[Customer_ID],Table1[[#This Row],[Customer_ID]],Table1[Sales]) -> 11576.38 | K20: =NOW() -> 46120.473
A21: CUST021 | B21: Arjun Sharma | C21: East | D21: Clothing | E21: 629.87 | F21: 4 | G21: 0.2 | H21: 45436 | I21: 256.15 | J21: =SUMIF(Table1[Customer_ID],Table1[[#This Row],[Customer_ID]],Table1[Sales]) -> 8044.2 | K21: =NOW() -> 46120.473
A22: CUST029 | B22: Swati Jain | C22: North | D22: Office Supplies | E22: 371.99 | F22: 10 | G22: 0.05 | H22: 45438 | I22: 130.9 | J22: =SUMIF(Table1[Customer_ID],Table1[[#This Row],[Customer_ID]],Table1[Sales]) -> 11216.81 | K22: =NOW() -> 46120.473
A23: CUST008 | B23: Ananya Mishra | C23: Central | D23: Electronics | E23: 342.28 | F23: 18 | G23: 0 | H23: 45439 | I23: 179.43 | J23: =SUMIF(Table1[Customer_ID],Table1[[#This Row],[Customer_ID]],Table1[Sales]) -> 7264.36 | K23: =NOW() -> 46120.473
A24: CUST026 | B24: Gaurav Singh | C24: East | D24: Office Supplies | E24: 1363.98 | F24: 20 | G24: 0.1 | H24: 45439 | I24: 663.51 | J24: =SUMIF(Table1[Customer_ID],Table1[[#This Row],[Customer_ID]],Table1[Sales]) -> 7997.81 | K24: =NOW() -> 46120.473
A25: CUST005 | B25: Pooja Mishra | C25: East | D25: Electronics | E25: 273.52 | F25: 20 | G25: 0.2 | H25: 45443 | I25: 61.72 | J25: =SUMIF(Table1[Customer_ID],Table1[[#This Row],[Customer_ID]],Table1[Sales]) -> 8197.96 | K25: =NOW() -> 46120.473
... A201: CUST013 | B201: Manoj Yadav | C201: East | D201: Furniture | E201: 1100.25 | F201: 14 | G201: 0 | H201: 45751 | I201: 264.11 | J201: =SUMIF(Table1[Customer_ID],Table1[[#This Row],[Customer_ID]],Table1[Sales]) -> 9513.89 | K201: =NOW() -> 46120.473

Sheet Scenario Summary
B2: Scenario Summary
D3: Current Values: | E3: No Discount | F3: 5% Discount | G3: 10% Discount | H3: 15% Discount | I3: 20% Discount
B5: Changing Cells:
C6: $R$5 | D6: 0.1 | E6: 0 | F6: 0.05 | G6: 0.1 | H6: 0.15 | I6: 0.2
B7: Result Cells:
C8: $R$6 | D8: 672.273 | E8: 746.97 | F8: 709.621 | G8: 672.273 | H8: 634.924 | I8: 597.576

Sheet Descriptive_Statistics
B3: Sales Descriptive Statistics
B5: Mean | C5: =AVERAGE(Customers_Data!E2:E201) -> 1051.1257
B6: Standard Error | C6: =STDEV(Customers_Data!E2:E201)/SQRT(COUNT(Customers_Data!E2:E201)) -> 33.876384
B7: Median | C7: =MEDIAN(Customers_Data!E2:E201) -> 1016.195
B8: Mode | C8: =IFERROR(MODE(Customers_Data!E2:E201),"N/A") -> N/A
B9: Standard Deviation | C9: =STDEV(Customers_Data!E2:E201) -> 479.08441
B10: Sample Variance | C10: =VAR(Customers_Data!E2:E201) -> 229521.88
B11: Kurtosis | C11: =KURT(Customers_Data!E2:E201) -> -1.1464208
B12: Skewness | C12: =SKEW(Customers_Data!E2:E201) -> 0.11181003
B13: Range | C13: =MAX(Customers_Data!E2:E201)-MIN(Customers_Data!E2:E201) -> 1649.1
B14: Minimum | C14: =MIN(Customers_Data!E2:E201) -> 262.72
B15: Maximum | C15: =MAX(Customers_Data!E2:E201) -> 1911.82
B16: Sum | C16: =SUM(Customers_Data!E2:E201) -> 210225.15
B17: Count | C17: =COUNT(Customers_Data!E2:E201) -> 200

Sheet Monthly_Sales
B2: Month | C2: Total Sales | D2: Growth % | E2: Trend
B3: 45383 | C3: =SUMIFS(Table1[Sales],Table1[Order_Date],">"&DATE(2024,4,1),Table1[Order_Date],"<="&DATE(2024,4,30)) -> 7436.71
B4: 45413 | C4: =SUMIFS(Table1[Sales],Table1[Order_Date],">"&DATE(2024,5,1),Table1[Order_Date],"<="&DATE(2024,5,30)) -> 13203.39 | D4: =(C4-C3)/C3 -> 0.7754343 | E4: =IF(D4>0,"▲ ","▼") -> ▲
B5: 45444 | C5: =SUMIFS(Table1[Sales],Table1[Order_Date],">"&DATE(2024,6,1),Table1[Order_Date],"<="&DATE(2024,6,30)) -> 19085.34 | D5: =(C5-C4)/C4 -> 0.44548786 | E5: =IF(D5>0,"▲ ","▼") -> ▲
B6: 45474 | C6: =SUMIFS(Table1[Sales],Table1[Order_Date],">"&DATE(2024,7,1),Table1[Order_Date],"<="&DATE(2024,7,30)) -> 14901.31 | D6: =(C6-C5)/C5 -> -0.21922743 | E6: =IF(D6>0,"▲ ","▼") -> ▼
B7: 45505 | C7: =SUMIFS(Table1[Sales],Table1[Order_Date],">"&DATE(2024,8,1),Table1[Order_Date],"<="&DATE(2024,8,30)) -> 13282.61 | D7: =(C7-C6)/C6 -> -0.10862803 | E7: =IF(D7>0,"▲ ","▼") -> ▼
B8: 45536 | C8: =SUMIFS(Table1[Sales],Table1[Order_Date],">"&DATE(2024,9,1),Table1[Order_Date],"<="&DATE(2024,9,30)) -> 20995.87 | D8: =(C8-C7)/C7 -> 0.58070364 | E8: =IF(D8>0,"▲ ","▼") -> ▲
B9: 45566 | C9: =SUMIFS(Table1[Sales],Table1[Order_Date],">"&DATE(2024,10,1),Table1[Order_Date],"<="&DATE(2024,10,31)) -> 10729.85 | D9: =(C9-C8)/C8 -> -0.48895426 | E9: =IF(D9>0,"▲ ","▼") -> ▼
B10: 45597 | C10: =SUMIFS(Table1[Sales],Table1[Order_Date],">"&DATE(2024,11,1),Table1[Order_Date],"<="&DATE(2024,11,30)) -> 19710.86 | D10: =(C10-C9)/C9 -> 0.8370117 | E10: =IF(D10>0,"▲ ","▼") -> ▲
B11: 45627 | C11: =SUMIFS(Table1[Sales],Table1[Order_Date],">"&DATE(2024,12,1),Table1[Order_Date],"<="&DATE(2024,12,31)) -> 15118.26 | D11: =(C11-C10)/C10 -> -0.23299846 | E11: =IF(D11>0,"▲ ","▼") -> ▼
B12: 45658 | C12: =SUMIFS(Table1[Sales],Table1[Order_Date],">"&DATE(2025,1,1),Table1[Order_Date],"<="&DATE(2025,1,30)) -> 12502.67 | D12: =(C12-C11)/C11 -> -0.17300867 | E12: =IF(D12>0,"▲ ","▼") -> ▼
B13: 45689 | C13: =SUMIFS(Table1[Sales],Table1[Order_Date],">"&DATE(2025,2,1),Table1[Order_Date],"<="&DATE(2025,2,30)) -> 24432.51 | D13: =(C13-C12)/C12 -> 0.95418339 | E13: =IF(D13>0,"▲ ","▼") -> ▲
B14: 45717 | C14: =SUMIFS(Table1[Sales],Table1[Order_Date],">"&DATE(2025,3,1),Table1[Order_Date],"<="&DATE(2025,3,30)) -> 20381.65 | D14: =(C14-C13)/C13 -> -0.16579795 | E14: =IF(D14>0,"▲ ","▼") -> ▼
B15: 45748 | C15: =SUMIFS(Table1[Sales],Table1[Order_Date],">"&DATE(2025,4,1),Table1[Order_Date],"<="&DATE(2025,4,30)) -> 2339.97 | D15: =(C15-C14)/C14 -> -0.88519232 | E15: =IF(D15>0,"▲ ","▼") -> ▼

Sheet High_value_Customers
A1: INDEX & MATCH Analysis | D1: High Value Threshold | E1: 10000
A2: Max Purchase Amount | B2: =MAX(Table1[Total_Purchase]) -> 11576.38 | D2: High Value Customer Count | E2: =COUNTIF(Table1[Total_Purchase],">"&E1) -> 58
A3: Top Customer Name | B3: =INDEX(Table1[Customer_Name],MATCH(B2,Table1[Total_Purchase],0)) -> Rahul Joshi
A4: Top Customer Region | B4: =INDEX(Table1[Region],MATCH(B2,Table1[Total_Purchase],0)) -> North
A5: Top Customer Sales | B5: =INDEX(Table1[Sales],MATCH(B2,Table1[Total_Purchase],0)) -> 1825.81
A11: Customer_ID | B11: Customer_Name | C11: Region | D11: Product_Category | E11: Sales | F11: Quantity | G11: Discount | H11: Order_Date | I11: Profit | J11: Total_Purchase | K11: Timestamp
A12: CUST003 | B12: Neha Iyer | C12: Central | D12: Furniture | E12: 1390.08 | F12: 18 | G12: 0.1 | H12: 45406 | I12: 334.13 | J12: 10564.12 | K12: =NOW() -> 46120.473
A13: CUST015 | B13: Rahul Joshi | C13: North | D13: Books | E13: 1825.81 | F13: 16 | G13: 0 | H13: 45425 | I13: 621.23 | J13: 11576.38 | K13: =NOW() -> 46120.473
A14: CUST003 | B14: Pooja Dubey | C14: West | D14: Office Supplies | E14: 942.38 | F14: 14 | G14: 0.2 | H14: 45429 | I14: 229.81 | J14: 10564.12 | K14: =NOW() -> 46120.473
A15: CUST015 | B15: Anjali Yadav | C15: West | D15: Electronics | E15: 1461.59 | F15: 14 | G15: 0.05 | H15: 45430 | I15: 532.49 | J15: 11576.38 | K15: =NOW() -> 46120.473
A16: CUST029 | B16: Swati Jain | C16: North | D16: Office Supplies | E16: 371.99 | F16: 10 | G16: 0.05 | H16: 45438 | I16: 130.9 | J16: 11216.81 | K16: =NOW() -> 46120.473
A17: CUST012 | B17: Anjali Bansal | C17: Central | D17: Clothing | E17: 515.78 | F17: 16 | G17: 0.05 | H17: 45447 | I17: 166.36 | J17: 10890.76 | K17: =NOW() -> 46120.473
A18: CUST012 | B18: Gaurav Jain | C18: Central | D18: Electronics | E18: 1255.84 | F18: 16 | G18: 0 | H18: 45449 | I18: 659.55 | J18: 10890.76 | K18: =NOW() -> 46120.473
A19: CUST023 | B19: Sneha Nair | C19: East | D19: Books | E19: 642.08 | F19: 7 | G19: 0.1 | H19: 45453 | I19: 295.36 | J19: 10167.54 | K19: =NOW() -> 46120.473
A20: CUST012 | B20: Tanvi Joshi | C20: North | D20: Clothing | E20: 1671.88 | F20: 15 | G20: 0 | H20: 45456 | I20: 373.72 | J20: 10890.76 | K20: =NOW() -> 46120.473
A21: CUST023 | B21: Sanjay Verma | C21: Central | D21: Electronics | E21: 773.76 | F21: 13 | G21: 0.1 | H21: 45457 | I21: 336.23 | J21: 10167.54 | K21: =NOW() -> 46120.473
A22: CUST012 | B22: Deepak Singh | C22: East | D22: Books | E22: 1503.3 | F22: 6 | G22: 0.05 | H22: 45459 | I22: 714.49 | J22: 10890.76 | K22: =NOW() -> 46120.473
A23: CUST015 | B23: Ananya Rao | C23: South | D23: Books | E23: 817.52 | F23: 18 | G23: 0 | H23: 45462 | I23: 206.66 | J23: 11576.38 | K23: =NOW() -> 46120.473
... A69: CUST023 | B69: Vikas Tiwari | C69: South | D69: Furniture | E69: 1239.72 | F69: 1 | G69: 0.05 | H69: 45749 | I69: 431.32 | J69: 10167.54 | K69: =NOW() -> 46120.473

Sheet Pivot_Table
A3: Sum of Sales | B3: Product_Category
A4: Region | B4: Electronics | C4: Clothing | D4: Books | E4: Furniture | F4: Office Supplies | G4: Grand Total
A5: Central | B5: =SUMIFS(Customers_Data!E2:E201,Customers_Data!C2:C201,A5,Customers_Data!D2:D201,B4) -> 9657.81 | C5: =SUMIFS(Customers_Data!E2:E201,Customers_Data!C2:C201,A5,Customers_Data!D2:D201,C4) -> 8650.82 | D5: =SUMIFS(Customers_Data!E2:E201,Customers_Data!C2:C201,A5,Customers_Data!D2:D201,D4) -> 8712.55 | E5: =SUMIFS(Customers_Data!E2:E201,Customers_Data!C2:C201,A5,Customers_Data!D2:D201,E4) -> 10635.84 | F5: =SUMIFS(Customers_Data!E2:E201,Customers_Data!C2:C201,A5,Customers_Data!D2:D201,F4) -> 5272.97 | G5: =SUM(B5:F5) -> 42929.99
A6: East | B6: =SUMIFS(Customers_Data!E2:E201,Customers_Data!C2:C201,A6,Customers_Data!D2:D201,B4) -> 15687.04 | C6: =SUMIFS(Customers_Data!E2:E201,Customers_Data!C2:C201,A6,Customers_Data!D2:D201,C4) -> 10335.44 | D6: =SUMIFS(Customers_Data!E2:E201,Customers_Data!C2:C201,A6,Customers_Data!D2:D201,D4) -> 4066.66 | E6: =SUMIFS(Customers_Data!E2:E201,Customers_Data!C2:C201,A6,Customers_Data!D2:D201,E4) -> 12439.81 | F6: =SUMIFS(Customers_Data!E2:E201,Customers_Data!C2:C201,A6,Customers_Data!D2:D201,F4) -> 9646.88 | G6: =SUM(B6:F6) -> 52175.83
A7: North | B7: =SUMIFS(Customers_Data!E2:E201,Customers_Data!C2:C201,A7,Customers_Data!D2:D201,B4) -> 9671.28 | C7: =SUMIFS(Customers_Data!E2:E201,Customers_Data!C2:C201,A7,Customers_Data!D2:D201,C4) -> 9969.75 | D7: =SUMIFS(Customers_Data!E2:E201,Customers_Data!C2:C201,A7,Customers_Data!D2:D201,D4) -> 2715.4 | E7: =SUMIFS(Customers_Data!E2:E201,Customers_Data!C2:C201,A7,Customers_Data!D2:D201,E4) -> 3724.5 | F7: =SUMIFS(Customers_Data!E2:E201,Customers_Data!C2:C201,A7,Customers_Data!D2:D201,F4) -> 8287.52 | G7: =SUM(B7:F7) -> 34368.45
A8: South | B8: =SUMIFS(Customers_Data!E2:E201,Customers_Data!C2:C201,A8,Customers_Data!D2:D201,B4) -> 2218.38 | C8: =SUMIFS(Customers_Data!E2:E201,Customers_Data!C2:C201,A8,Customers_Data!D2:D201,C4) -> 6421.11 | D8: =SUMIFS(Customers_Data!E2:E201,Customers_Data!C2:C201,A8,Customers_Data!D2:D201,D4) -> 11505.14 | E8: =SUMIFS(Customers_Data!E2:E201,Customers_Data!C2:C201,A8,Customers_Data!D2:D201,E4) -> 9037.71 | F8: =SUMIFS(Customers_Data!E2:E201,Customers_Data!C2:C201,A8,Customers_Data!D2:D201,F4) -> 5072.95 | G8: =SUM(B8:F8) -> 34255.29
A9: West | B9: =SUMIFS(Customers_Data!E2:E201,Customers_Data!C2:C201,A9,Customers_Data!D2:D201,B4) -> 13916.72 | C9: =SUMIFS(Customers_Data!E2:E201,Customers_Data!C2:C201,A9,Customers_Data!D2:D201,C4) -> 3361.99 | D9: =SUMIFS(Customers_Data!E2:E201,Customers_Data!C2:C201,A9,Customers_Data!D2:D201,D4) -> 10096.28 | E9: =SUMIFS(Customers_Data!E2:E201,Customers_Data!C2:C201,A9,Customers_Data!D2:D201,E4) -> 10054.95 | F9: =SUMIFS(Customers_Data!E2:E201,Customers_Data!C2:C201,A9,Customers_Data!D2:D201,F4) -> 9065.65 | G9: =SUM(B9:F9) -> 46495.59
A10: Grand Total | B10: =SUM(B5:B9) -> 51151.23 | C10: =SUM(C5:C9) -> 38739.11 | D10: =SUM(D5:D9) -> 37096.03 | E10: =SUM(E5:E9) -> 45892.81 | F10: =SUM(F5:F9) -> 37345.97 | G10: =SUM(G5:G9) -> 210225.15

Sheet Charts
D2: Region | E2: Sum of Sales | K2: Months (Order_Date) | L2: Sum of Sales | U2: Product_Category | V2: Count of Sales
D3: Central | E3: =SUMIF(Customers_Data!C2:C201,D3,Customers_Data!E2:E201) -> 42929.99 | K3: Jan | L3: =SUMPRODUCT((MONTH(Customers_Data!H2:H201)=1)*(YEAR(Customers_Data!H2:H201)>=2024)*Customers_Data!E2:E201) -> 13185.04 | U3: Electronics | V3: =COUNTIF(Customers_Data!D2:D201,U3) -> 45
D4: East | E4: =SUMIF(Customers_Data!C2:C201,D4,Customers_Data!E2:E201) -> 52175.83 | K4: Feb | L4: =SUMPRODUCT((MONTH(Customers_Data!H2:H201)=2)*(YEAR(Customers_Data!H2:H201)>=2024)*Customers_Data!E2:E201) -> 24426.57 | U4: Clothing | V4: =COUNTIF(Customers_Data!D2:D201,U4) -> 40
D5: North | E5: =SUMIF(Customers_Data!C2:C201,D5,Customers_Data!E2:E201) -> 34368.45 | K5: Mar | L5: =SUMPRODUCT((MONTH(Customers_Data!H2:H201)=3)*(YEAR(Customers_Data!H2:H201)>=2024)*Customers_Data!E2:E201) -> 22048.98 | U5: Books | V5: =COUNTIF(Customers_Data!D2:D201,U5) -> 31
D6: South | E6: =SUMIF(Customers_Data!C2:C201,D6,Customers_Data!E2:E201) -> 34255.29 | K6: Apr | L6: =SUMPRODUCT((MONTH(Customers_Data!H2:H201)=4)*(YEAR(Customers_Data!H2:H201)>=2024)*Customers_Data!E2:E201) -> 11185.24 | U6: Furniture | V6: =COUNTIF(Customers_Data!D2:D201,U6) -> 42
D7: West | E7: =SUMIF(Customers_Data!C2:C201,D7,Customers_Data!E2:E201) -> 46495.59 | K7: May | L7: =SUMPRODUCT((MONTH(Customers_Data!H2:H201)=5)*(YEAR(Customers_Data!H2:H201)>=2024)*Customers_Data!E2:E201) -> 14571.73 | U7: Office Supplies | V7: =COUNTIF(Customers_Data!D2:D201,U7) -> 42
D8: Grand Total | E8: =SUM(E3:E7) -> 210225.15 | K8: Jun | L8: =SUMPRODUCT((MONTH(Customers_Data!H2:H201)=6)*(YEAR(Customers_Data!H2:H201)>=2024)*Customers_Data!E2:E201) -> 19085.34 | U8: Grand Total | V8: =SUM(V3:V7) -> 200
K9: Jul | L9: =SUMPRODUCT((MONTH(Customers_Data!H2:H201)=7)*(YEAR(Customers_Data!H2:H201)>=2024)*Customers_Data!E2:E201) -> 19702.26
K10: Aug | L10: =SUMPRODUCT((MONTH(Customers_Data!H2:H201)=8)*(YEAR(Customers_Data!H2:H201)>=2024)*Customers_Data!E2:E201) -> 16260.43
K11: Sep | L11: =SUMPRODUCT((MONTH(Customers_Data!H2:H201)=9)*(YEAR(Customers_Data!H2:H201)>=2024)*Customers_Data!E2:E201) -> 22490.74
K12: Oct | L12: =SUMPRODUCT((MONTH(Customers_Data!H2:H201)=10)*(YEAR(Customers_Data!H2:H201)>=2024)*Customers_Data!E2:E201) -> 11800.11
K13: Nov | L13: =SUMPRODUCT((MONTH(Customers_Data!H2:H201)=11)*(YEAR(Customers_Data!H2:H201)>=2024)*Customers_Data!E2:E201) -> 20350.45
K14: Dec | L14: =SUMPRODUCT((MONTH(Customers_Data!H2:H201)=12)*(YEAR(Customers_Data!H2:H201)>=2024)*Customers_Data!E2:E201) -> 15118.26
K15: Grand Total | L15: =SUM(L3:L14) -> 210225.15

Sheet Dashboard
B2: SALES PERFORMANCE DASHBOARD | 2024 - 2025
B4: TOTAL SALES | D4: TOTAL PROFIT | F4: TOTAL CUSTOMERS | H4: TOP CUSTOMER
B5: =SUM(Customers_Data!E2:E201) -> 210225.15 | D5: =SUM(Customers_Data!J2:J201) -> 1581430 | F5: =COUNTA(Customers_Data!A2:A201) -> 200 | H5: =INDEX(Customers_Data!B2:B201,MATCH(MAX(Customers_Data!J2:J201),Customers_Data!J2:J201,0)) -> Rahul Joshi
B7: AVG ORDER VALUE | D7: MAX PURCHASE | F7: TOTAL ORDERS | H7: PROFIT MARGIN
B8: =AVERAGE(Customers_Data!E2:E201) -> 1051.1257 | D8: =MAX(Table1[Total_Purchase]) -> 11576.38 | F8: =COUNTA(Customers_Data!A2:A201) -> 200 | H8: =SUM(Customers_Data!I2:I201)/SUM(Customers_Data!E2:E201) -> 0.36940304
